[
  {
    "image": "https://www.ikea.com/dk/da/images/products/vatnestroem-pocket-sprung-mattress__0789642_PE764084_S5.jpg?f=xxs",
    "title": "VATNESTRÖM",
    "integer": "2.999",
    "price": "2.999 €",
    "decimal": ".00",
    "description": "Springmadras med pocketfjedre90x200 cm"
  },
  {
    "image": "https://www.ikea.com/dk/da/images/products/luddros-mattress-protector__0789885_PE764184_S5.jpg?f=xxs",
    "title": "LUDDROS",
    "integer": "39",
    "price": "39 €",
    "decimal": ".00",
    "description": "Rullemadras90x200 cm"
  },
  {
    "image": "https://www.ikea.com/dk/da/images/products/grusnarv-mattress-protector__0790191_PE764297_S5.jpg?f=xxs",
    "title": "GRUSNARV",
    "integer": "119",
    "price": "119 €",
    "decimal": ".00",
    "description": "Rullemadras90x200 cm"
  },
  {
    "image": "https://www.ikea.com/dk/da/images/products/aengskorn-mattress-protector__0789895_PE764189_S5.jpg?f=xxs",
    "title": "ÄNGSKORN",
    "integer": "299",
    "price": "299 €",
    "decimal": ".00",
    "description": "Rullemadras140x200 cm"
  },
  {
    "image": "https://www.ikea.com/dk/da/images/products/luddros-pillow-protector__0789755_PE764155_S5.jpg?f=xxs",
    "title": "LUDDROS",
    "integer": "19",
    "price": "19 €",
    "decimal": ".00",
    "description": "Pudebeskytter60x70 cm"
  },
  {
    "image": "https://www.ikea.com/dk/da/images/products/jaernudda-sprung-base-incl-mattress-pad__0098013_PE238917_S5.jpg?f=xxs",
    "title": "JÄRNUDDA",
    "integer": "549",
    "price": "549 €",
    "decimal": ".00",
    "description": "Boxmadras med topmadras90x200 cm"
  },
  {
    "image": "https://www.ikea.com/dk/da/images/products/hamarvik-sprung-mattress-firm-dark-beige__0210693_PE364275_S5.jpg?f=xxs",
    "title": "HAMARVIK",
    "integer": "1.199",
    "price": "1.199 €",
    "decimal": ".00",
    "description": "Springmadras140x200 cm"
  },
  {
    "image": "https://www.ikea.com/dk/da/images/products/moshult-foam-mattress__0641874_PE700765_S5.jpg?f=xxs",
    "title": "MOSHULT",
    "integer": "399",
    "price": "399 €",
    "decimal": ".00",
    "description": "Skummadras90x200 cm"
  },
  {
    "image": "https://www.ikea.com/dk/da/images/products/skarer-wooden-base-spring-mattress__0425651_PE581468_S5.jpg?f=xxs",
    "title": "SKÅRER",
    "integer": "1.899",
    "price": "1.899 €",
    "decimal": ".00",
    "description": "Boxmadras140x200 cm"
  },
  {
    "image": "https://www.ikea.com/dk/da/images/products/malfors-foam-mattress__0636883_PE698072_S5.jpg?f=xxs",
    "title": "MALFORS",
    "integer": "599",
    "price": "599 €",
    "decimal": ".00",
    "description": "Skummadras90x200 cm"
  },
  {
    "image": "https://www.ikea.com/dk/da/images/products/snarum-wooden-base-sprung-mattress__0641889_PE700777_S5.jpg?f=xxs",
    "title": "SNARUM",
    "integer": "1.299",
    "price": "1.299 €",
    "decimal": ".00",
    "description": "Boxmadras140x200 cm"
  },
  {
    "image": "https://www.ikea.com/dk/da/images/products/snarum-mattress-and-mattress-pad__0642038_PE700846_S5.jpg?f=xxs",
    "title": "SNARUM",
    "integer": "1.509",
    "price": "1.509 €",
    "decimal": ".00",
    "description": "Madras og topmadras120x200 cm"
  },
  {
    "image": "https://www.ikea.com/dk/da/images/products/malvik-foam-mattress__0243545_PE382879_S5.jpg?f=xxs",
    "title": "MALVIK",
    "integer": "799",
    "price": "799 €",
    "decimal": ".00",
    "description": "Skummadras90x200 cm"
  },
  {
    "image": "https://www.ikea.com/dk/da/images/products/hoevag-pocket-sprung-mattress-firm-dark-grey__0210701_PE364283_S5.jpg?f=xxs",
    "title": "HÖVÅG",
    "integer": "1.799",
    "price": "1.799 €",
    "decimal": ".00",
    "description": "Springmadras med pocketfjedre140x200 cm"
  },
  {
    "image": "https://www.ikea.com/dk/da/images/products/tuddal-mattress-pad-white__0641079_PE700243_S5.jpg?f=xxs",
    "title": "TUDDAL",
    "integer": "600",
    "price": "600 €",
    "decimal": ".00",
    "description": "Topmadras140x200 cm"
  },
  {
    "image": "https://www.ikea.com/dk/da/images/products/husvika-sprung-mattress-firm__0641856_PE700743_S5.jpg?f=xxs",
    "title": "HUSVIKA",
    "integer": "549",
    "price": "549 €",
    "decimal": ".00",
    "description": "Springmadras80x200 cm"
  },
  {
    "image": "https://www.ikea.com/dk/da/images/products/skarer-mattress-and-mattress-pad__0396560_PE562384_S5.jpg?f=xxs",
    "title": "SKÅRER",
    "integer": "2.609",
    "price": "2.609 €",
    "decimal": ".00",
    "description": "Madras og topmadras140x200 cm"
  },
  {
    "image": "https://www.ikea.com/dk/da/images/products/siggerud-mattress-wedge__0641110_PE700258_S5.jpg?f=xxs",
    "title": "SIGGERUD",
    "integer": "80",
    "price": "80 €",
    "decimal": ".00",
    "description": "Madraskile195 cm"
  },
  {
    "image": "https://www.ikea.com/dk/da/images/products/jaernudda-sprung-base-incl-mattress-pad__0781121_PE760510_S5.jpg?f=xxs",
    "title": "JÄRNUDDA",
    "integer": "739",
    "price": "739 €",
    "decimal": ".00",
    "description": "Boxmadras med topmadras90x200 cm"
  },
  {
    "image": "https://www.ikea.com/dk/da/images/products/hyllestad-pocket-sprung-mattress__0190898_PE344625_S5.jpg?f=xxs",
    "title": "HYLLESTAD",
    "integer": "2.999",
    "price": "2.999 €",
    "decimal": ".00",
    "description": "Springmadras med pocketfjedre160x200 cm"
  },
  {
    "image": "https://www.ikea.com/dk/da/images/products/morgedal-latex-mattress__0243562_PE382888_S5.jpg?f=xxs",
    "title": "MORGEDAL",
    "integer": "2.299",
    "price": "2.299 €",
    "decimal": ".00",
    "description": "Latexmadras160x200 cm"
  },
  {
    "image": "https://www.ikea.com/dk/da/images/products/skotterud-wooden-base-sprung-mattress__0395435_PE562576_S5.jpg?f=xxs",
    "title": "SKOTTERUD",
    "integer": "1.899",
    "price": "1.899 €",
    "decimal": ".00",
    "description": "Boxmadras90x200 cm"
  },
  {
    "image": "https://www.ikea.com/dk/da/images/products/talgje-mattress-pad-white__0641080_PE700240_S5.jpg?f=xxs",
    "title": "TALGJE",
    "integer": "450",
    "price": "450 €",
    "decimal": ".00",
    "description": "Topmadras140x200 cm"
  },
  {
    "image": "https://www.ikea.com/dk/da/images/products/morgedal-foam-mattress-firm-dark-grey__0243558_PE382884_S5.jpg?f=xxs",
    "title": "MORGEDAL",
    "integer": "2.299",
    "price": "2.299 €",
    "decimal": ".00",
    "description": "Skummadras160x200 cm"
  }
]
